<?xml version="1.0" encoding="UTF-8" standalone="no"?>
<root>
    <name>Running Away in Fear</name>
    <data>
        <item>ε=ε=(っ*´□`)っ</item>
        <item>ε=ε=(怒ﾟДﾟ)ﾉ</item>
        <item>=͟͟͞͞ =͟͟͞͞ ﾍ( ´Д`)ﾉ</item>
        <item>ヽ(￣д￣;)ノ=3=3=3</item>
        <item>٩(´Д` ;)۶:.*</item>
        <item>(´×д×`三꒪д꒪ ;)</item>
        <item>– =͟͟͞͞ =͟͟͞͞ ﾍ( ´Д`)ﾉ</item>
        <item>ε＝ε＝ε＝(((((ﾉ｀･Д･)ﾉ</item>
        <item>(◞º❒º)◞₎₎(◟º❑º)◟⁾⁾➟➠➨</item>
        <item>ε=٩(●❛ö❛)۶</item>
        <item>Σ(ﾟДﾟ；≡；ﾟдﾟ)</item>
        <item>(c=(c=(c=(c=(ﾟﾛﾟ;c=</item>
        <item>⊂(ﾟДﾟ;⊂⌒`つ</item>
        <item>..･ヾ(。￣□￣)ﾂ</item>
        <item>≡≡≡=(ﾉTдT)ﾉ</item>
        <item>ε=ε=(⊃≧□≦)⊃</item>
        <item>!!Σ(ﾟДﾟ;≡≡≡≡≡ヾ(;ﾟдﾟ)/</item>
        <item>┃ ु ⠁⃘ ⠁⃘ू┃⁼³₌₃</item>
        <item>༻(〃ຶ⌂〃ຶ)</item>
        <item>ਭ३౽=͟͟͞͞(((ഽʻ⁸ʻ)ഽ</item>
        <item>ε=ε=ε=(ﾉ≧∀)ﾉ</item>
        <item>(❛ӧ❛三❛ӧ❛)</item>
        <item>Σ(°Д°；≡；°д°)</item>
        <item>ε=ε=ε=(ﾉTдT)ﾉ</item>
        <item>～ε～ε～┌(|||´Д｀)ノ</item>
        <item>゛(ﾉ~o~)ﾉ</item>
        <item>ε=ε=ε=┏(ﾟロﾟ;)┛</item>
        <item>ε==ε==(ﾉ゜д゜)ﾂ</item>
        <item>ヽ(д`ヽ)｡｡</item>
        <item>｡｡(ﾉ´д)ﾉ</item>
        <item>ヽ(´Д｀;≡;´Д｀)丿</item>
        <item>((ヽ(´Д`;ゞ=ヾ;´Д`)ﾉ))</item>
        <item>ヽ(ω；`ヽ))…((ﾉ´；ω)ﾉ</item>
        <item>ヽ(д｀ヽ彡ﾉ´д)ﾉ</item>
        <item>ε=ε=ε=(((怒ﾟДﾟ)ﾉﾉ</item>
        <item>ε=ε=ε=(*ﾉ´Д｀)ﾉﾟ</item>
        <item>ヾ(*゜、ω゜*)ﾉﾟ</item>
        <item>!!((((((っ;ﾟ∀ﾟ)っ</item>
        <item>へ( ʘ͡ ₒ ʘ͡ )╮/\╱\</item>
        <item>（（（（（（（（　゜□゜）ノ</item>
        <item>ヾ(･c_,･｡) ﾉ =з =з= з</item>
        <item>｡｡゛(ﾉ&gt;&lt;)ﾉ</item>
        <item>ε≡Ξ≡Ξ≡ヽ( ;￣〇￣)ﾉ</item>
        <item>ヽ(ﾟ□ﾟ＼*≡*／ﾟ□ﾟ)ﾉ</item>
        <item>ε＝（ﾉﾟдﾟ）ﾉ</item>
        <item>(＾ω＾ ≡ °д°)</item>
        <item>ヾ(((;ꈡ▱ꈡ;)))ﾉ</item>
        <item>✧.*(⌯ⅉॕੰૈ▱ⅉॕੰૈ)</item>
        <item>★⌒Ｙ⌒Ｙ⌒Ｙ⌒Ｙ⌒ ヾ(oﾟДﾟ)ﾉ</item>
        <item>へ(~Д~*へ))))… …((((ノ*~З~)ノ</item>
        <item>（´□｀；）=З=З=З=З=З=З</item>
    </data>
</root>