<?xml version="1.0" encoding="UTF-8"?>
<root>
    <name>Single Line Nosebleeds</name>
    <data>
        <item>( ￣┏＿┓￣)</item>
        <item>ヽ(◎´┏∀┓｀)ノ</item>
        <item>(￣┏Д┓￣°*)</item>
        <item>༼つ☉┏益┓⊙༽つ</item>
        <item>(ノ≧┏Д┓≦)ノ</item>
        <item>(*ﾟ┏∇┓ﾟ)</item>
        <item>(ﾟ┏∇┓ﾟ*)</item>
        <item>ヽ༼ຈ┏ل͜┓ຈ༽ﾉ</item>
        <item>⋋▐ ◔ ┏ل͜┓ ◔ ▐⋌</item>
        <item>w(′┏▽┓`●)w</item>
        <item>【●･´┏ω┓`･●】</item>
        <item>(￣┏Д┓￣ )</item>
        <item>ﾐ(´┏ω┓｀)/</item>
        <item>o(●′┏＿┓`)o</item>
        <item>ᕕ║ ˵ ᴼ ┏ل͜┓ ᴼ ˵ ║⊃</item>
        <item>o(ﾟ┏∀┓ﾟo)</item>
        <item>(´┏･┓｀)</item>
        <item>ヾ(ﾟ┏д┓ﾟ)ﾉ゛</item>
        <item>(oﾟ┏ω┓ﾟo)</item>
        <item>乁╏ ಠ ┏ل͜┓ ಠ ╏ㄏ</item>
        <item>┌〳 ՞ ┏ل͜┓ ՞ 〵┐</item>
        <item>(oﾟ┏Д┓ﾟ)o</item>
        <item>｡ﾟ(ﾟ´┏∀┓｀*ﾟ)ﾟ｡</item>
        <item>(*´┏ｴ┓｀*)</item>
        <item>～(´┏ω┓｀～)</item>
        <item>(´o・┏ω┓・o｀)</item>
        <item>(´┏o┓｀)</item>
        <item>(～´┏ω┓｀)～</item>
        <item>(￣┏∞┓￣)</item>
        <item>|*￣┏Д┓￣|┛</item>
        <item>(＾┌_̀┐＾)</item>
        <item>Σ(；ﾟ┏д┓ﾟ)_</item>
        <item>┗|￣┏Д┓￣*|</item>
        <item>( ˇ෴ˇ )</item>
        <item>(༎ຶ ෴ ༎ຶ)</item>
        <item>༼ ༎ຶ ෴ ༎ຶ༽</item>
        <item>(⚫ે෴ۜ⚫)</item>
        <item>ᕦ⊙෴⊙ᕤ</item>
        <item>◝₍⁽ֹ෴ֹ⁾₎◜</item>
        <item>[ ◯ ෴ ◯ ]</item>
        <item>| ・ ෴ ・ |</item>
        <item>ԅ(◉෴◉ԅ)</item>
        <item>┌། ิ ෴ ิ །┐</item>
        <item>(ಠ .̫.̫ ಠ)</item>
        <item>(•̴̑⁎̵̭•̴̆)</item>
        <item>✌(꒡͡ ો ̼̮ ꒡͡✌)</item>
        <item>(　˙灬˙　)</item>
        <item>❛ॕ̀ੇ≀ ̼❛ॕ̀ੇ˵</item>
        <item>(⁰︻⁰)</item>
        <item>(-◞८࿆◟࿆-)</item>
        <item>(&amp;gt;̯-̮&amp;lt;̯)</item>
        <item>٩(-̃_̮̮̃-̃)۶</item>
        <item>(˗̆ˍ̂˗)</item>
        <item>(•˳̂•̆)</item>
        <item>◟( ͡° ʃヮɭ ͡°)ﾉ</item>
        <item>ᕙ། ¯ ~͜ʖ~ ¯ །ᕗ</item>
        <item>ヽ(∴｀┗Д┛´)ﾉ</item>
        <item>(⋆ʾ ˙̫̮ ʿ⋆)</item>
        <item>σ(●ﾟ┏∀┛｡●)ﾉ</item>
        <item>m(￣&amp;lt;ス&amp;gt;￣)m</item>
        <item>m(￣&amp;lt;マ&amp;gt;￣)m</item>
        <item>m(￣&amp;lt;ン&amp;gt;￣)m</item>
        <item>The Professor</item>
        <item>。(⌒෴⌒。)</item>
        <item>The Fu Manchu</item>
        <item>(｀ ┏ ∀ ┓ ´)</item>
        <item>The Abra Kadabra</item>
        <item>且_(゜ ˒̫̮ ゜；)ノﾞ</item>
        <item>The TORGUE!!!</item>
        <item>ᕙ(๏益๏)ᕗ</item>
        <item>The Oil Baron</item>
        <item>ヽ(･ ˒̫̮･)ﾉ</item>
        <item>It’s ok if you can’t grow a moustache.</item>
        <item>(⁎·́෴·̀)◞ ͂͂(˒̩̩̥́௰˓̩̩̥̀⁎)</item>
        <item>The Dandy</item>
        <item>o(´~∀~｀*)</item>
        <item>The Funny Uncle</item>
        <item>٩(^෴^)۶</item>
        <item>The Push-Broom</item>
        <item>o(^ 灬 ^)o</item>
        <item>The Businessman</item>
        <item>(•̀ ⑉̈•́)و ̑̑</item>
        <item>The Englishman</item>
        <item>ƪ(˘︷ ˘)و</item>
        <item>The Magnum</item>
        <item>ԅ( ˘ ▂ ˘ ԅ)</item>
        <item>The Vanilla Bean</item>
        <item>(¬ ₀̑ ¬)</item>
        <item>The Coffee Connoisseur</item>
        <item>(っ˘ ˒̫̮ ˘ς)</item>
        <item>The Mustachio</item>
        <item>୧(﹒︠ ̫ ̫̊ ̫﹒︡)୨</item>
        <item>The Paintbrush</item>
        <item>【・ ˡ̲̮ ・】</item>
        <item>The Goatee</item>
        <item>꒰๑• ˳̫̬•๑꒱</item>
        <item>The Undercover Brother</item>
        <item>(⁰︻⁰)</item>
        <item>The El Bandito</item>
        <item>ಠ ~_~ ಠ</item>
        <item>The Hercule Poirot</item>
        <item>| ू•ૅ •̫̮ •́)ᵎᵎᵎ</item>
        <item>The Prospector</item>
        <item>(－ ˑ̭ ლ)</item>
        <item>The Swashbuckler</item>
        <item>˛˛ꉂ ◞•̀︷•́)੭̸</item>
        <item>The Neighbourino</item>
        <item>┐(^▂ ^；)┌</item>
        <item>The Horseshoe</item>
        <item>( ►┏_┓◄ )</item>
        <item>_(꒪ཀ꒪」∠)_</item>
        <item>(ヾﾉ꒪ཫ꒪ )</item>
        <item>(꒪ཀ꒪)</item>
        <item>( °٢° )</item>
        <item>ˉ̡̠̭̭”( ⑉¯ །། ¯⑉ )ˉ̡̠̭̭”</item>
        <item>(＾་།＾)</item>
        <item>(-́◞८͙༙◟-̀)</item>
        <item>ᶘ○་།○ᶅ</item>
        <item>(꒪ิཫ꒪ )ノิิิ ḟ৹ʳᵧ৹ᵤ</item>
        <item>（´〃｀＊）</item>
        <item>(´ii｀)</item>
        <item>（￣ ¨ヽ￣ ）</item>
        <item>(￣TT￣)</item>
        <item>(´ノi｀)</item>
        <item>(￣^;￣)</item>
        <item>(￣ＴＴ￣)</item>
        <item>(￣TT￣)</item>
        <item>(￣ ;￣)</item>
        <item>(￣-;￣)</item>
        <item>(￣￣ξ￣￣)</item>
        <item>(￣ii￣)</item>
        <item>(￣ii￣*)</item>
        <item>(￣Γ￣)</item>
        <item>(*￣ii￣)</item>
        <item>{{{(￣ﾊ￣*)}}}</item>
        <item>( ´ ii ｀ )</item>
        <item>（￣￣ｉｉ￣￣）</item>
        <item>⁽͑˙˚̀༎˚́˙⁾̉</item>
    </data>
</root>